{
  "v": "5.12.1",
  "fr": 30,
  "ip": 0,
  "op": 120,
  "w": 200,
  "h": 200,
  "nm": "project_card_fixed",
  "ddd": 0,
  "assets": [],
  "layers": [
    {
      "ddd": 0,
      "ind": 1,
      "ty": 4,
      "nm": "bg",
      "sr": 1,
      "ks": { "o": { "a": 0, "k": 100 }, "r": { "a": 0, "k": 0 }, "p": { "a": 0, "k": [100, 100, 0] }, "a": { "a": 0, "k": [0, 0, 0] }, "s": { "a": 0, "k": [100, 100, 100] } },
      "ao": 0,
      "shapes": [{ "ty": "gr", "it": [
        { "ty": "rc", "p": { "a": 0, "k": [0, 0] }, "s": { "a": 0, "k": [200, 200] }, "r": { "a": 0, "k": 16 }, "nm": "rect" },
        { "ty": "fl", "c": { "a": 0, "k": [0.106, 0.157, 0.306, 1] }, "o": { "a": 0, "k": 100 }, "r": 1, "nm": "fill" },
        { "ty": "tr", "p": { "a": 0, "k": [0, 0] }, "a": { "a": 0, "k": [0, 0] }, "s": { "a": 0, "k": [100, 100] }, "r": { "a": 0, "k": 0 }, "o": { "a": 0, "k": 100 }, "sk": { "a": 0, "k": 0 }, "sa": { "a": 0, "k": 0 } }
      ], "nm": "bg_group", "np": 2, "cix": 2, "bm": 0, "ix": 1, "hd": false }],
      "ip": 0,
      "op": 120,
      "st": 0,
      "bm": 0
    },
    {
      "ddd": 0,
      "ind": 2,
      "ty": 4,
      "nm": "charts",
      "sr": 1,
      "ks": { "o": { "a": 0, "k": 100 }, "r": { "a": 0, "k": 0 }, "p": { "a": 0, "k": [48, 62, 0] }, "a": { "a": 0, "k": [0, 0, 0] }, "s": { "a": 0, "k": [100, 100, 100] } },
      "ao": 0,
      "shapes": [
        { "ty": "gr", "it": [
          { "ty": "rc", "p": { "a": 0, "k": [0, 0] }, "s": { "a": 0, "k": [64, 44] }, "r": { "a": 0, "k": 6 }, "nm": "panel" },
          { "ty": "fl", "c": { "a": 0, "k": [0.96, 0.96, 0.96, 1] }, "o": { "a": 0, "k": 100 }, "r": 1, "nm": "fill" },
          { "ty": "tr", "p": { "a": 0, "k": [0, 0] }, "a": { "a": 0, "k": [0, 0] }, "s": { "a": 0, "k": [100, 100] }, "r": { "a": 0, "k": 0 }, "o": { "a": 0, "k": 100 }, "sk": { "a": 0, "k": 0 }, "sa": { "a": 0, "k": 0 } }
        ], "nm": "panel_group", "np": 2, "cix": 2, "bm": 0, "ix": 1, "hd": false },
        { "ty": "gr", "it": [
          { "ty": "rc", "p": { "a": 0, "k": [-16, 8] }, "s": { "a": 0, "k": [8, 14] }, "r": { "a": 0, "k": 1 }, "nm": "bar1" },
          { "ty": "fl", "c": { "a": 0, "k": [1, 0.6, 0.15, 1] }, "o": { "a": 0, "k": 100 }, "r": 1, "nm": "fill" },
          { "ty": "tr", "p": { "a": 0, "k": [0, 0] }, "a": { "a": 0, "k": [0, 0] }, "s": { "a": 0, "k": [100, 100] }, "r": { "a": 0, "k": 0 }, "o": { "a": 0, "k": 100 }, "sk": { "a": 0, "k": 0 }, "sa": { "a": 0, "k": 0 } }
        ], "nm": "bar1_group", "np": 2, "cix": 2, "bm": 0, "ix": 2, "hd": false },
        { "ty": "gr", "it": [
          { "ty": "rc", "p": { "a": 0, "k": [0, 4] }, "s": { "a": 0, "k": [8, 22] }, "r": { "a": 0, "k": 1 }, "nm": "bar2" },
          { "ty": "fl", "c": { "a": 0, "k": [0.2, 0.45, 0.85, 1] }, "o": { "a": 0, "k": 100 }, "r": 1, "nm": "fill" },
          { "ty": "tr", "p": { "a": 0, "k": [0, 0] }, "a": { "a": 0, "k": [0, 0] }, "s": { "a": 0, "k": [100, 100] }, "r": { "a": 0, "k": 0 }, "o": { "a": 0, "k": 100 }, "sk": { "a": 0, "k": 0 }, "sa": { "a": 0, "k": 0 } }
        ], "nm": "bar2_group", "np": 2, "cix": 2, "bm": 0, "ix": 3, "hd": false },
        { "ty": "gr", "it": [
          { "ty": "rc", "p": { "a": 0, "k": [16, 0] }, "s": { "a": 0, "k": [8, 30] }, "r": { "a": 0, "k": 1 }, "nm": "bar3" },
          { "ty": "fl", "c": { "a": 0, "k": [0.45, 0.82, 0.35, 1] }, "o": { "a": 0, "k": 100 }, "r": 1, "nm": "fill" },
          { "ty": "tr", "p": { "a": 0, "k": [0, 0] }, "a": { "a": 0, "k": [0, 0] }, "s": { "a": 0, "k": [100, 100] }, "r": { "a": 0, "k": 0 }, "o": { "a": 0, "k": 100 }, "sk": { "a": 0, "k": 0 }, "sa": { "a": 0, "k": 0 } }
        ], "nm": "bar3_group", "np": 2, "cix": 2, "bm": 0, "ix": 4, "hd": false }
      ],
      "ip": 0,
      "op": 120,
      "st": 0,
      "bm": 0
    },
    {
      "ddd": 0,
      "ind": 3,
      "ty": 4,
      "nm": "printer_paper",
      "sr": 1,
      "ks": {
        "o": { "a": 0, "k": 100 },
        "r": { "a": 0, "k": 0 },
        "p": { "a": 1, "k": [
          { "t": 0, "s": [44, 138, 0] },
          { "t": 30, "s": [44, 128, 0] },
          { "t": 60, "s": [44, 138, 0] },
          { "t": 90, "s": [44, 128, 0] },
          { "t": 119, "s": [44, 138, 0] }
        ] },
        "a": { "a": 0, "k": [0, 0, 0] },
        "s": { "a": 0, "k": [100, 100, 100] }
      },
      "ao": 0,
      "shapes": [{ "ty": "gr", "it": [
        { "ty": "rc", "p": { "a": 0, "k": [0, 0] }, "s": { "a": 0, "k": [18, 22] }, "r": { "a": 0, "k": 2 }, "nm": "paper" },
        { "ty": "fl", "c": { "a": 0, "k": [1, 1, 1, 1] }, "o": { "a": 0, "k": 100 }, "r": 1, "nm": "fill" },
        { "ty": "tr", "p": { "a": 0, "k": [0, 0] }, "a": { "a": 0, "k": [0, 0] }, "s": { "a": 0, "k": [100, 100] }, "r": { "a": 0, "k": 0 }, "o": { "a": 0, "k": 100 }, "sk": { "a": 0, "k": 0 }, "sa": { "a": 0, "k": 0 } }
      ], "nm": "paper_group", "np": 2, "cix": 2, "bm": 0, "ix": 1, "hd": false }],
      "ip": 0,
      "op": 120,
      "st": 0,
      "bm": 0
    },
    {
      "ddd": 0,
      "ind": 4,
      "ty": 4,
      "nm": "printer_body",
      "sr": 1,
      "ks": { "o": { "a": 0, "k": 100 }, "r": { "a": 0, "k": 0 }, "p": { "a": 0, "k": [44, 152, 0] }, "a": { "a": 0, "k": [0, 0, 0] }, "s": { "a": 0, "k": [100, 100, 100] } },
      "ao": 0,
      "shapes": [{ "ty": "gr", "it": [
        { "ty": "rc", "p": { "a": 0, "k": [0, 0] }, "s": { "a": 0, "k": [34, 24] }, "r": { "a": 0, "k": 4 }, "nm": "body" },
        { "ty": "fl", "c": { "a": 0, "k": [0.7, 0.72, 0.76, 1] }, "o": { "a": 0, "k": 100 }, "r": 1, "nm": "fill" },
        { "ty": "tr", "p": { "a": 0, "k": [0, 0] }, "a": { "a": 0, "k": [0, 0] }, "s": { "a": 0, "k": [100, 100] }, "r": { "a": 0, "k": 0 }, "o": { "a": 0, "k": 100 }, "sk": { "a": 0, "k": 0 }, "sa": { "a": 0, "k": 0 } }
      ], "nm": "printer_group", "np": 2, "cix": 2, "bm": 0, "ix": 1, "hd": false }],
      "ip": 0,
      "op": 120,
      "st": 0,
      "bm": 0
    },
    {
      "ddd": 0,
      "ind": 5,
      "ty": 4,
      "nm": "boxes",
      "sr": 1,
      "ks": { "o": { "a": 0, "k": 100 }, "r": { "a": 0, "k": 0 }, "p": { "a": 0, "k": [162, 160, 0] }, "a": { "a": 0, "k": [0, 0, 0] }, "s": { "a": 0, "k": [100, 100, 100] } },
      "ao": 0,
      "shapes": [
        { "ty": "gr", "it": [
          { "ty": "rc", "p": { "a": 0, "k": [-8, 4] }, "s": { "a": 0, "k": [20, 16] }, "r": { "a": 0, "k": 2 }, "nm": "b1" },
          { "ty": "fl", "c": { "a": 0, "k": [1, 0.68, 0.24, 1] }, "o": { "a": 0, "k": 100 }, "r": 1, "nm": "fill" },
          { "ty": "tr", "p": { "a": 0, "k": [0, 0] }, "a": { "a": 0, "k": [0, 0] }, "s": { "a": 0, "k": [100, 100] }, "r": { "a": 0, "k": 0 }, "o": { "a": 0, "k": 100 }, "sk": { "a": 0, "k": 0 }, "sa": { "a": 0, "k": 0 } }
        ], "nm": "b1_group", "np": 2, "cix": 2, "bm": 0, "ix": 1, "hd": false },
        { "ty": "gr", "it": [
          { "ty": "rc", "p": { "a": 0, "k": [10, -6] }, "s": { "a": 0, "k": [18, 14] }, "r": { "a": 0, "k": 2 }, "nm": "b2" },
          { "ty": "fl", "c": { "a": 0, "k": [1, 0.6, 0.15, 1] }, "o": { "a": 0, "k": 100 }, "r": 1, "nm": "fill" },
          { "ty": "tr", "p": { "a": 0, "k": [0, 0] }, "a": { "a": 0, "k": [0, 0] }, "s": { "a": 0, "k": [100, 100] }, "r": { "a": 0, "k": 0 }, "o": { "a": 0, "k": 100 }, "sk": { "a": 0, "k": 0 }, "sa": { "a": 0, "k": 0 } }
        ], "nm": "b2_group", "np": 2, "cix": 2, "bm": 0, "ix": 2, "hd": false }
      ],
      "ip": 0,
      "op": 120,
      "st": 0,
      "bm": 0
    }
  ]
}
